{"file_name": "imagesr__r__l__z__rlz20d00__521107137+-7140.tif", "documents": [{"VendorName": "JONES. DAY. REAVIS & POGUE", "VendorName_conf": 0.76, "VendorAddress": {"house_number": null, "po_box": null, "road": "LAKESIDE AVENUE", "city": "CLEVELAND", "state": "OHIO", "postal_code": "44114", "country_region": null, "street_address": "LAKESIDE AVENUE"}, "VendorAddress_conf": 0.48, "VendorAddressRecipient": "NORTH POINT", "VendorAddressRecipient_conf": 0.543, "CustomerName": "Mary R. Ward, Esquire\nCounsel - R&D\nR.J. Reynolds Tobacco Company\nBowman Gray Technical Center", "CustomerName_conf": 0.669, "CustomerId": "556655-009-033", "CustomerId_conf": 0.907, "CustomerAddress": {"house_number": "1100", "po_box": null, "road": "Reynolds Boulevard", "city": "Winston-Salem", "state": "NC", "postal_code": "27102", "country_region": null, "street_address": "1100 Reynolds Boulevard"}, "CustomerAddress_conf": 0.866, "CustomerAddressRecipient": "Mary R. Ward, Esquire\nCounsel - R&D\nR.J. Reynolds Tobacco Company\nBowman Gray Technical Center", "CustomerAddressRecipient_conf": 0.669, "InvoiceId": "01510540", "InvoiceId_conf": 0.906, "InvoiceDate": "1995-11-15", "InvoiceDate_conf": 0.905, "InvoiceTotal": 1035.0, "InvoiceTotal_conf": 0.374, "Items": [{"Description": "To all legal services rendered\nfrom September 1, 1995 through\nOctober 21, 1995 in connection with\nthe Indoor Air Quality (OSEA) matter", "Description_conf": 0.416, "Quantity": 32.75, "Quantity_conf": 0.588, "Amount": 9550.0, "Amount_conf": 0.925}], "ServiceStartDate": "1995-09-01", "ServiceStartDate_conf": 0.899, "ServiceEndDate": "1995-10-21", "ServiceEndDate_conf": 0.822, "RemittanceAddress": {"house_number": null, "po_box": null, "road": null, "city": "CLEVELAND", "state": "OHIO", "postal_code": "44189", "country_region": null, "street_address": ""}, "RemittanceAddress_conf": 0.513}]}